{
  "city": "shanghai",
  "city_name": "Shanghai",
  "date": "2026-03-25",
  "unit": "C",
  "station": "ZSPD",
  "event_end_date": "2026-03-25T12:00:00Z",
  "hours_at_discovery": 7.2,
  "status": "closed",
  "position": null,
  "actual_temp": null,
  "resolved_outcome": null,
  "pnl": null,
  "forecast_snapshots": [
    {
      "ts": "2026-03-25T04:47:13.370110+00:00",
      "horizon": "D+0",
      "hours_left": 7.2,
      "ecmwf": 15.2,
      "hrrr": null,
      "metar": 16.0,
      "best": 15.2,
      "best_source": "ecmwf"
    },
    {
      "ts": "2026-03-25T04:52:21.919892+00:00",
      "horizon": "D+0",
      "hours_left": 7.1,
      "ecmwf": 15.2,
      "hrrr": null,
      "metar": 16.0,
      "best": 15.2,
      "best_source": "ecmwf"
    },
    {
      "ts": "2026-03-25T05:00:52.945024+00:00",
      "horizon": "D+0",
      "hours_left": 7.0,
      "ecmwf": 15.2,
      "hrrr": null,
      "metar": 16.0,
      "best": 15.2,
      "best_source": "ecmwf"
    },
    {
      "ts": "2026-03-25T06:01:23.924806+00:00",
      "horizon": "D+0",
      "hours_left": 6.0,
      "ecmwf": 15.2,
      "hrrr": null,
      "metar": 16.0,
      "best": 15.2,
      "best_source": "ecmwf"
    },
    {
      "ts": "2026-03-25T07:01:43.425563+00:00",
      "horizon": "D+0",
      "hours_left": 5.0,
      "ecmwf": 15.2,
      "hrrr": null,
      "metar": 16.0,
      "best": 15.2,
      "best_source": "ecmwf"
    },
    {
      "ts": "2026-03-25T08:04:38.135611+00:00",
      "horizon": "D+0",
      "hours_left": 3.9,
      "ecmwf": 15.2,
      "hrrr": null,
      "metar": 16.0,
      "best": 15.2,
      "best_source": "ecmwf"
    },
    {
      "ts": "2026-03-25T08:18:55.099595+00:00",
      "horizon": "D+0",
      "hours_left": 3.7,
      "ecmwf": 15.3,
      "hrrr": null,
      "metar": 16.0,
      "best": 15.3,
      "best_source": "ecmwf"
    },
    {
      "ts": "2026-03-25T09:01:26.453387+00:00",
      "horizon": "D+0",
      "hours_left": 3.0,
      "ecmwf": 15.3,
      "hrrr": null,
      "metar": 15.0,
      "best": 15.3,
      "best_source": "ecmwf"
    },
    {
      "ts": "2026-03-25T10:01:43.927083+00:00",
      "horizon": "D+0",
      "hours_left": 2.0,
      "ecmwf": 15.3,
      "hrrr": null,
      "metar": 14.0,
      "best": 15.3,
      "best_source": "ecmwf"
    },
    {
      "ts": "2026-03-25T11:02:06.074758+00:00",
      "horizon": "D+0",
      "hours_left": 1.0,
      "ecmwf": 15.3,
      "hrrr": null,
      "metar": 13.0,
      "best": 15.3,
      "best_source": "ecmwf"
    },
    {
      "ts": "2026-03-25T12:01:55.729373+00:00",
      "horizon": "D+0",
      "hours_left": 0.0,
      "ecmwf": 15.3,
      "hrrr": null,
      "metar": 12.0,
      "best": 15.3,
      "best_source": "ecmwf"
    },
    {
      "ts": "2026-03-25T13:02:09.617348+00:00",
      "horizon": "D+0",
      "hours_left": 0.0,
      "ecmwf": 15.3,
      "hrrr": null,
      "metar": 12.0,
      "best": 15.3,
      "best_source": "ecmwf"
    },
    {
      "ts": "2026-03-25T14:01:59.713307+00:00",
      "horizon": "D+0",
      "hours_left": 0.0,
      "ecmwf": 15.3,
      "hrrr": null,
      "metar": 11.0,
      "best": 15.3,
      "best_source": "ecmwf"
    },
    {
      "ts": "2026-03-25T15:02:20.365314+00:00",
      "horizon": "D+0",
      "hours_left": 0.0,
      "ecmwf": 15.3,
      "hrrr": null,
      "metar": 11.0,
      "best": 15.3,
      "best_source": "ecmwf"
    },
    {
      "ts": "2026-03-25T16:02:38.501587+00:00",
      "horizon": "D+0",
      "hours_left": 0.0,
      "ecmwf": null,
      "hrrr": null,
      "metar": 10.0,
      "best": null,
      "best_source": null
    },
    {
      "ts": "2026-03-25T17:02:38.134560+00:00",
      "horizon": "D+0",
      "hours_left": 0.0,
      "ecmwf": null,
      "hrrr": null,
      "metar": 10.0,
      "best": null,
      "best_source": null
    },
    {
      "ts": "2026-03-25T18:02:35.390120+00:00",
      "horizon": "D+0",
      "hours_left": 0.0,
      "ecmwf": null,
      "hrrr": null,
      "metar": 10.0,
      "best": null,
      "best_source": null
    },
    {
      "ts": "2026-03-25T19:02:27.072722+00:00",
      "horizon": "D+0",
      "hours_left": 0.0,
      "ecmwf": null,
      "hrrr": null,
      "metar": 10.0,
      "best": null,
      "best_source": null
    },
    {
      "ts": "2026-03-25T20:02:49.643920+00:00",
      "horizon": "D+0",
      "hours_left": 0.0,
      "ecmwf": null,
      "hrrr": null,
      "metar": 9.0,
      "best": null,
      "best_source": null
    },
    {
      "ts": "2026-03-25T21:03:06.711385+00:00",
      "horizon": "D+0",
      "hours_left": 0.0,
      "ecmwf": null,
      "hrrr": null,
      "metar": 10.0,
      "best": null,
      "best_source": null
    },
    {
      "ts": "2026-03-25T22:02:55.621561+00:00",
      "horizon": "D+0",
      "hours_left": 0.0,
      "ecmwf": null,
      "hrrr": null,
      "metar": 10.0,
      "best": null,
      "best_source": null
    },
    {
      "ts": "2026-03-25T23:02:51.663098+00:00",
      "horizon": "D+0",
      "hours_left": 0.0,
      "ecmwf": null,
      "hrrr": null,
      "metar": 11.0,
      "best": null,
      "best_source": null
    }
  ],
  "market_snapshots": [
    {
      "ts": "2026-03-25T04:47:13.370110+00:00",
      "top_bucket": "17.0-17.0C",
      "top_price": 0.655
    },
    {
      "ts": "2026-03-25T04:52:21.919892+00:00",
      "top_bucket": "17.0-17.0C",
      "top_price": 0.67
    },
    {
      "ts": "2026-03-25T05:00:52.945024+00:00",
      "top_bucket": "17.0-17.0C",
      "top_price": 0.635
    },
    {
      "ts": "2026-03-25T06:01:23.924806+00:00",
      "top_bucket": "16.0-16.0C",
      "top_price": 0.64
    },
    {
      "ts": "2026-03-25T07:01:43.425563+00:00",
      "top_bucket": "16.0-16.0C",
      "top_price": 0.9
    },
    {
      "ts": "2026-03-25T08:04:38.135611+00:00",
      "top_bucket": "16.0-16.0C",
      "top_price": 0.992
    },
    {
      "ts": "2026-03-25T08:18:55.099595+00:00",
      "top_bucket": "16.0-16.0C",
      "top_price": 0.9935
    },
    {
      "ts": "2026-03-25T09:01:26.453387+00:00",
      "top_bucket": "16.0-16.0C",
      "top_price": 0.994
    },
    {
      "ts": "2026-03-25T10:01:43.927083+00:00",
      "top_bucket": "16.0-16.0C",
      "top_price": 0.998
    },
    {
      "ts": "2026-03-25T11:02:06.074758+00:00",
      "top_bucket": "16.0-16.0C",
      "top_price": 0.997
    },
    {
      "ts": "2026-03-25T12:01:55.729373+00:00",
      "top_bucket": "16.0-16.0C",
      "top_price": 0.999
    },
    {
      "ts": "2026-03-25T13:02:09.617348+00:00",
      "top_bucket": "16.0-16.0C",
      "top_price": 0.9995
    },
    {
      "ts": "2026-03-25T14:01:59.713307+00:00",
      "top_bucket": "16.0-16.0C",
      "top_price": 0.9995
    },
    {
      "ts": "2026-03-25T15:02:20.365314+00:00",
      "top_bucket": "16.0-16.0C",
      "top_price": 0.9995
    },
    {
      "ts": "2026-03-25T16:02:38.501587+00:00",
      "top_bucket": "16.0-16.0C",
      "top_price": 0.9995
    },
    {
      "ts": "2026-03-25T17:02:38.134560+00:00",
      "top_bucket": "16.0-16.0C",
      "top_price": 0.9995
    },
    {
      "ts": "2026-03-25T18:02:35.390120+00:00",
      "top_bucket": "16.0-16.0C",
      "top_price": 0.9995
    },
    {
      "ts": "2026-03-25T19:02:27.072722+00:00",
      "top_bucket": "16.0-16.0C",
      "top_price": 1.0
    },
    {
      "ts": "2026-03-25T20:02:49.643920+00:00",
      "top_bucket": "16.0-16.0C",
      "top_price": 1.0
    },
    {
      "ts": "2026-03-25T21:03:06.711385+00:00",
      "top_bucket": "16.0-16.0C",
      "top_price": 1.0
    },
    {
      "ts": "2026-03-25T22:02:55.621561+00:00",
      "top_bucket": "16.0-16.0C",
      "top_price": 1.0
    },
    {
      "ts": "2026-03-25T23:02:51.663098+00:00",
      "top_bucket": "16.0-16.0C",
      "top_price": 1.0
    }
  ],
  "all_outcomes": [
    {
      "question": "Will the highest temperature in Shanghai be 11°C or below on March 25?",
      "market_id": "1670884",
      "range": [
        -999.0,
        11.0
      ],
      "bid": 0.0,
      "ask": 1.0,
      "price": 0.0,
      "spread": 1.0,
      "volume": 48228.0
    },
    {
      "question": "Will the highest temperature in Shanghai be 12°C on March 25?",
      "market_id": "1670885",
      "range": [
        12.0,
        12.0
      ],
      "bid": 0.0,
      "ask": 1.0,
      "price": 0.0,
      "spread": 1.0,
      "volume": 7076.0
    },
    {
      "question": "Will the highest temperature in Shanghai be 13°C on March 25?",
      "market_id": "1670886",
      "range": [
        13.0,
        13.0
      ],
      "bid": 0.0,
      "ask": 1.0,
      "price": 0.0,
      "spread": 1.0,
      "volume": 11235.0
    },
    {
      "question": "Will the highest temperature in Shanghai be 14°C on March 25?",
      "market_id": "1670887",
      "range": [
        14.0,
        14.0
      ],
      "bid": 0.0,
      "ask": 1.0,
      "price": 0.0,
      "spread": 1.0,
      "volume": 20192.0
    },
    {
      "question": "Will the highest temperature in Shanghai be 15°C on March 25?",
      "market_id": "1670888",
      "range": [
        15.0,
        15.0
      ],
      "bid": 0.0,
      "ask": 1.0,
      "price": 0.0,
      "spread": 1.0,
      "volume": 49663.0
    },
    {
      "question": "Will the highest temperature in Shanghai be 16°C on March 25?",
      "market_id": "1670889",
      "range": [
        16.0,
        16.0
      ],
      "bid": 1.0,
      "ask": 0.0,
      "price": 1.0,
      "spread": -1.0,
      "volume": 73373.0
    },
    {
      "question": "Will the highest temperature in Shanghai be 17°C on March 25?",
      "market_id": "1670890",
      "range": [
        17.0,
        17.0
      ],
      "bid": 0.0,
      "ask": 1.0,
      "price": 0.0,
      "spread": 1.0,
      "volume": 38264.0
    },
    {
      "question": "Will the highest temperature in Shanghai be 18°C on March 25?",
      "market_id": "1670891",
      "range": [
        18.0,
        18.0
      ],
      "bid": 0.0,
      "ask": 1.0,
      "price": 0.0,
      "spread": 1.0,
      "volume": 50616.0
    },
    {
      "question": "Will the highest temperature in Shanghai be 19°C on March 25?",
      "market_id": "1670892",
      "range": [
        19.0,
        19.0
      ],
      "bid": 0.0,
      "ask": 1.0,
      "price": 0.0,
      "spread": 1.0,
      "volume": 68619.0
    },
    {
      "question": "Will the highest temperature in Shanghai be 20°C on March 25?",
      "market_id": "1670893",
      "range": [
        20.0,
        20.0
      ],
      "bid": 0.0,
      "ask": 1.0,
      "price": 0.0,
      "spread": 1.0,
      "volume": 34939.0
    },
    {
      "question": "Will the highest temperature in Shanghai be 21°C or higher on March 25?",
      "market_id": "1670894",
      "range": [
        21.0,
        999.0
      ],
      "bid": 0.0,
      "ask": 1.0,
      "price": 0.0,
      "spread": 1.0,
      "volume": 21993.0
    }
  ],
  "created_at": "2026-03-25T04:47:15.010539+00:00"
}